[
  {
    "/projects/{id}/triggers": {
      "get": {
        "summary": "List project triggers",
        "description": "Get a list of project’s build triggers.",
        "operationId": "listProjectTriggers",
        "parameters": [
          {
            "name": "id",
            "in": "path",
            "description": "The ID or URL-encoded path of the project owned by the authenticated user",
            "required": true,
            "schema": {
              "type": "string"
            }
          }
        ],
        "responses": {
          "200": {
            "description": "successful operation",
            "content": {
              "application/json": {
                "schema": {
                  "type": "array",
                  "items": {
                    "type": "object",
                    "properties": {
                      "id": {
                        "type": "integer"
                      },
                      "description": {
                        "type": "string"
                      },
                      "created_at": {
                        "type": "string"
                      },
                      "last_used": {
                        "type": "string"
                      },
                      "token": {
                        "type": "string"
                      },
                      "updated_at": {
                        "type": "string"
                      },
                      "owner": {
                        "type": "string"
                      }
                    }
                  }
                }
              }
            }
          }
        }
      }
    }
  },
  {
    "/projects/{id}/triggers/:trigger_id": {
      "get": {
        "summary": "Get trigger details",
        "description": "Get details of project’s build trigger.",
        "operationId": "getTriggerDetails",
        "parameters": [
          {
            "name": "id",
            "in": "path",
            "description": "The ID or URL-encoded path of the project owned by the authenticated user",
            "required": true,
            "schema": {
              "type": "string"
            }
          },
          {
            "name": "trigger_id",
            "in": "path",
            "description": "The trigger ID",
            "required": true,
            "schema": {
              "type": "integer"
            }
          }
        ],
        "responses": {
          "200": {
            "description": "successful operation",
            "content": {
              "application/json": {
                "schema": {
                  "type": "object",
                  "properties": {
                    "id": {
                      "type": "integer"
                    },
                    "description": {
                      "type": "string"
                    },
                    "created_at": {
                      "type": "string"
                    },
                    "last_used": {
                      "type": "string"
                    },
                    "token": {
                      "type": "string"
                    },
                    "updated_at": {
                      "type": "string"
                    },
                    "owner": {
                      "type": "string"
                    }
                  }
                }
              }
            }
          }
        }
      }
    }
  },
  {
    "/projects/{id}/triggers": {
      "post": {
        "summary": "Create a project trigger",
        "description": "Create a trigger for a project.",
        "operationId": "createAProjectTrigger",
        "parameters": [
          {
            "name": "id",
            "in": "path",
            "description": "The ID or URL-encoded path of the project owned by the authenticated user",
            "required": true,
            "schema": {
              "type": "string"
            }
          },
          {
            "name": "description",
            "in": "query",
            "description": "The trigger name",
            "required": true,
            "schema": {
              "type": "string"
            }
          }
        ],
        "responses": {
          "200": {
            "description": "successful operation",
            "content": {
              "application/json": {
                "schema": {
                  "type": "object",
                  "properties": {
                    "id": {
                      "type": "integer"
                    },
                    "description": {
                      "type": "string"
                    },
                    "created_at": {
                      "type": "string"
                    },
                    "last_used": {
                      "type": "string"
                    },
                    "token": {
                      "type": "string"
                    },
                    "updated_at": {
                      "type": "string"
                    },
                    "owner": {
                      "type": "string"
                    }
                  }
                }
              }
            }
          }
        }
      }
    }
  },
  {
    "/projects/{id}/triggers/:trigger_id": {
      "put": {
        "summary": "Update a project trigger",
        "description": "Update a trigger for a project.",
        "operationId": "updateAProjectTrigger",
        "parameters": [
          {
            "name": "id",
            "in": "path",
            "description": "The ID or URL-encoded path of the project owned by the authenticated user",
            "required": true,
            "schema": {
              "type": "string"
            }
          },
          {
            "name": "trigger_id",
            "in": "path",
            "description": "The trigger ID",
            "required": true,
            "schema": {
              "type": "integer"
            }
          },
          {
            "name": "description",
            "in": "query",
            "description": "The trigger name",
            "required": false,
            "schema": {
              "type": "string"
            }
          }
        ],
        "responses": {
          "200": {
            "description": "successful operation",
            "content": {
              "application/json": {
                "schema": {
                  "type": "object",
                  "properties": {
                    "id": {
                      "type": "integer"
                    },
                    "description": {
                      "type": "string"
                    },
                    "created_at": {
                      "type": "string"
                    },
                    "last_used": {
                      "type": "string"
                    },
                    "token": {
                      "type": "string"
                    },
                    "updated_at": {
                      "type": "string"
                    },
                    "owner": {
                      "type": "string"
                    }
                  }
                }
              }
            }
          }
        }
      }
    }
  },
  {
    "/projects/{id}/triggers/:trigger_id": {
      "delete": {
        "summary": "Remove a project trigger",
        "description": "Remove a project’s build trigger.",
        "operationId": "removeAProjectTrigger",
        "parameters": [
          {
            "name": "id",
            "in": "path",
            "description": "The ID or URL-encoded path of the project owned by the authenticated user",
            "required": true,
            "schema": {
              "type": "string"
            }
          },
          {
            "name": "trigger_id",
            "in": "path",
            "description": "The trigger ID",
            "required": true,
            "schema": {
              "type": "integer"
            }
          }
        ],
        "responses": {
          "200": {
            "description": "successful operation",
            "content": {
              "application/json": {
                "schema": {
                  "type": "string"
                }
              }
            }
          }
        }
      }
    }
  }
]